okbloomer/__init__.py
okbloomer/bloom_filter.py
okbloomer/py.typed
okbloomer-0.0.4.dist-info/licenses/LICENSE
okbloomer-0.0.4.dist-info/METADATA
okbloomer-0.0.4.dist-info/WHEEL
okbloomer-0.0.4.dist-info/top_level.txt
okbloomer-0.0.4.dist-info/RECORD
