Metadata-Version: 2.4
Name: OkBloomer
Version: 0.0.4
Summary: An implementation of the OkBloomer algorithm, an autoscaling Bloom filter with ultra-low memory footprint for Python.
Author-email: Andrew DalPino <andrewdalpino@icloud.com>
License: MIT
Project-URL: Homepage, https://github.com/andrewdalpino/PyBloomer
Project-URL: Documentation, https://github.com/andrewdalpino/PyBloomer/README.md
Project-URL: Source, https://github.com/andrewdalpino/PyBloomer
Requires-Python: >=3.10
License-File: LICENSE
Requires-Dist: mmh3>5.0.0
Requires-Dist: nptyping>=2.5.0
Requires-Dist: numpy>=1.19.5
Provides-Extra: dev
Requires-Dist: mypy; extra == "dev"
Requires-Dist: black; extra == "dev"
Provides-Extra: test
Requires-Dist: mypy; extra == "test"
Requires-Dist: black; extra == "test"
Dynamic: license-file
